{"frames":[{"filename":"coin1","frame":{"x":29,"y":0,"w":15,"h":17},"rotated":false,"trimmed":false,"spriteSourceSize":{"x":0,"y":0,"w":15,"h":17},"sourceSize":{"w":15,"h":17}},{"filename":"coin2","frame":{"x":14,"y":18,"w":13,"h":17},"rotated":false,"trimmed":false,"spriteSourceSize":{"x":0,"y":0,"w":13,"h":17},"sourceSize":{"w":13,"h":17}},{"filename":"coin3","frame":{"x":31,"y":36,"w":12,"h":17},"rotated":false,"trimmed":false,"spriteSourceSize":{"x":0,"y":0,"w":12,"h":17},"sourceSize":{"w":12,"h":17}},{"filename":"coin4","frame":{"x":0,"y":0,"w":11,"h":17},"rotated":false,"trimmed":false,"spriteSourceSize":{"x":0,"y":0,"w":11,"h":17},"sourceSize":{"w":11,"h":17}},{"filename":"coin5","frame":{"x":12,"y":0,"w":5,"h":17},"rotated":false,"trimmed":false,"spriteSourceSize":{"x":0,"y":0,"w":5,"h":17},"sourceSize":{"w":5,"h":17}},{"filename":"coin6","frame":{"x":18,"y":0,"w":10,"h":17},"rotated":false,"trimmed":false,"spriteSourceSize":{"x":0,"y":0,"w":10,"h":17},"sourceSize":{"w":10,"h":17}},{"filename":"coin7","frame":{"x":18,"y":36,"w":12,"h":17},"rotated":false,"trimmed":false,"spriteSourceSize":{"x":0,"y":0,"w":12,"h":17},"sourceSize":{"w":12,"h":17}},{"filename":"coin8","frame":{"x":0,"y":18,"w":13,"h":17},"rotated":false,"trimmed":false,"spriteSourceSize":{"x":0,"y":0,"w":13,"h":17},"sourceSize":{"w":13,"h":17}},{"filename":"coin9","frame":{"x":29,"y":18,"w":15,"h":17},"rotated":false,"trimmed":false,"spriteSourceSize":{"x":0,"y":0,"w":15,"h":17},"sourceSize":{"w":15,"h":17}},{"filename":"coin10","frame":{"x":0,"y":36,"w":17,"h":17},"rotated":false,"trimmed":false,"spriteSourceSize":{"x":0,"y":0,"w":17,"h":17},"sourceSize":{"w":17,"h":17}}],"meta":{"app":"https://www.leshylabs.com/apps/sstool/","version":"Leshy SpriteSheet Tool v0.8.4","image":"coin.png","size":{"w":44,"h":53},"scale":1}}